jvm_mcp_server/__init__.py
jvm_mcp_server/__main__.py
jvm_mcp_server/config.py
jvm_mcp_server/connection_pool.py
jvm_mcp_server/server.py
jvm_mcp_server/native/__init__.py
jvm_mcp_server/native/base.py
jvm_mcp_server/native/tools/__init__.py
jvm_mcp_server/native/tools/class_info.py
jvm_mcp_server/native/tools/javap.py
jvm_mcp_server/native/tools/jcmd.py
jvm_mcp_server/native/tools/jinfo.py
jvm_mcp_server/native/tools/jmap.py
jvm_mcp_server/native/tools/jps.py
jvm_mcp_server/native/tools/jstack.py
jvm_mcp_server/native/tools/jstat.py
jvm_mcp_server/tests/test_native/__init__.py
jvm_mcp_server/tests/test_native/test_class_info.py
jvm_mcp_server/tests/test_native/test_javap.py
jvm_mcp_server/tests/test_native/test_jcmd.py
jvm_mcp_server/tests/test_native/test_jinfo.py
jvm_mcp_server/tests/test_native/test_jmap.py
jvm_mcp_server/tests/test_native/test_jps.py
jvm_mcp_server/tests/test_native/test_jstack.py
jvm_mcp_server/tests/test_native/test_jstat.py
mseep_jvm_mcp_server-0.1.7.dist-info/METADATA
mseep_jvm_mcp_server-0.1.7.dist-info/WHEEL
mseep_jvm_mcp_server-0.1.7.dist-info/entry_points.txt
mseep_jvm_mcp_server-0.1.7.dist-info/licenses/LICENSE
mseep_jvm_mcp_server-0.1.7.dist-info/RECORD
